devstack/__init__.py
devstack/cmd.py
devstack/dsconf.py
devstack/tests/__init__.py
devstack/tests/base.py
devstack/tests/test_devstack.py
devstack/tests/test_ini_add.py
devstack/tests/test_ini_comment.py
devstack/tests/test_ini_remove.py
devstack/tests/test_ini_set.py
devstack/tests/test_ini_uncomment.py
devstack/tests/test_localconf_extract.py
devstack/tests/test_localconf_merge.py
devstack/tests/test_localconf_set.py
devstack/tests/test_localconf_set_local.py
devstack_tools-2.0.0.dist-info/AUTHORS
devstack_tools-2.0.0.dist-info/LICENSE
devstack_tools-2.0.0.dist-info/METADATA
devstack_tools-2.0.0.dist-info/WHEEL
devstack_tools-2.0.0.dist-info/entry_points.txt
devstack_tools-2.0.0.dist-info/pbr.json
devstack_tools-2.0.0.dist-info/top_level.txt
devstack_tools-2.0.0.dist-info/RECORD
